{
  "meta": {
    "match_id": 3813313,
    "home": "ATK Mohun Bagan",
    "away": "Odisha",
    "home_color_raw": "#0a1628",
    "home_color": "#2e65b7",
    "away_color_raw": "#c9d1d9",
    "away_color": "#c9d1d9",
    "score_home": 0,
    "score_away": 0,
    "penalty_home": null,
    "penalty_away": null,
    "has_extra_time": false,
    "has_penalties": false,
    "max_minute": 92,
    "xg_home": 2.043,
    "xg_away": 0.644,
    "shots_home": 17,
    "shots_away": 13,
    "possession_home": 54.2,
    "competition": "Indian Super league",
    "season": "2021/2022",
    "date": "2022-01-23"
  },
  "xg_flow": {
    "minutes": [
      0,
      1,
      2,
      3,
      4,
      5,
      6,
      7,
      8,
      9,
      10,
      11,
      12,
      13,
      14,
      15,
      16,
      17,
      18,
      19,
      20,
      21,
      22,
      23,
      24,
      25,
      26,
      27,
      28,
      29,
      30,
      31,
      32,
      33,
      34,
      35,
      36,
      37,
      38,
      39,
      40,
      41,
      42,
      43,
      44,
      45,
      46,
      47,
      48,
      49,
      50,
      51,
      52,
      53,
      54,
      55,
      56,
      57,
      58,
      59,
      60,
      61,
      62,
      63,
      64,
      65,
      66,
      67,
      68,
      69,
      70,
      71,
      72,
      73,
      74,
      75,
      76,
      77,
      78,
      79,
      80,
      81,
      82,
      83,
      84,
      85,
      86,
      87,
      88,
      89,
      90,
      91
    ],
    "home": [
      0.0,
      0.0,
      0.0,
      0.0,
      0.0,
      0.0,
      0.1218,
      0.1218,
      0.1218,
      0.1218,
      0.1218,
      0.1218,
      0.1218,
      0.1419,
      0.5137,
      0.5137,
      0.5137,
      0.5137,
      0.5379,
      0.604,
      0.604,
      0.604,
      0.604,
      0.604,
      0.6118,
      0.6719,
      0.8596,
      0.8596,
      1.2654,
      1.2654,
      1.2654,
      1.2654,
      1.2654,
      1.2654,
      1.4581,
      1.4581,
      1.4581,
      1.4581,
      1.5274,
      1.5274,
      1.5274,
      1.5274,
      1.5274,
      1.5274,
      1.5274,
      1.5274,
      1.5274,
      1.5274,
      1.5274,
      1.5274,
      1.8099,
      1.8099,
      1.8099,
      1.8099,
      1.8099,
      1.8099,
      1.8099,
      1.8099,
      1.8099,
      1.8099,
      1.8099,
      1.8099,
      1.8099,
      1.8099,
      1.8099,
      1.8099,
      1.8099,
      1.8099,
      1.8099,
      1.8151,
      1.8151,
      1.8151,
      1.8151,
      1.8151,
      1.8151,
      1.8151,
      1.8151,
      1.8151,
      1.8151,
      1.8151,
      1.8151,
      1.8151,
      1.8151,
      1.8151,
      1.8151,
      1.8151,
      1.8151,
      1.8151,
      2.0426,
      2.0426,
      2.0426,
      2.0426
    ],
    "away": [
      0.0,
      0.0,
      0.0,
      0.1004,
      0.1004,
      0.1004,
      0.1004,
      0.1004,
      0.1004,
      0.1827,
      0.1827,
      0.1827,
      0.1827,
      0.1827,
      0.1827,
      0.1827,
      0.1827,
      0.1827,
      0.1827,
      0.1827,
      0.207,
      0.2448,
      0.2448,
      0.254,
      0.254,
      0.254,
      0.254,
      0.254,
      0.254,
      0.254,
      0.254,
      0.254,
      0.254,
      0.254,
      0.254,
      0.254,
      0.254,
      0.254,
      0.254,
      0.254,
      0.254,
      0.254,
      0.254,
      0.254,
      0.254,
      0.2743,
      0.2743,
      0.2743,
      0.2743,
      0.2743,
      0.2743,
      0.2743,
      0.2743,
      0.2743,
      0.3215,
      0.3658,
      0.5108,
      0.5108,
      0.5108,
      0.5108,
      0.5108,
      0.5108,
      0.5108,
      0.5108,
      0.5108,
      0.5108,
      0.5394,
      0.5733,
      0.5733,
      0.5733,
      0.5733,
      0.5733,
      0.5733,
      0.6152,
      0.6152,
      0.6152,
      0.6152,
      0.6152,
      0.6152,
      0.6152,
      0.6152,
      0.6152,
      0.6152,
      0.6152,
      0.6152,
      0.6152,
      0.6152,
      0.6152,
      0.6152,
      0.6152,
      0.6152,
      0.6441
    ],
    "pressure_home": [
      0.1724,
      0.2759,
      0.2759,
      0.2759,
      0.2759,
      0.2759,
      0.3793,
      0.3793,
      0.3793,
      0.3793,
      0.3966,
      0.2931,
      0.2931,
      0.4483,
      0.5862,
      0.5862,
      0.4828,
      0.4828,
      0.569,
      0.6379,
      0.4655,
      0.4655,
      0.4655,
      0.3103,
      0.2241,
      0.4655,
      0.6897,
      0.6897,
      0.6724,
      0.6034,
      0.5862,
      0.5862,
      0.5862,
      0.6207,
      0.6207,
      0.3793,
      0.1552,
      0.1552,
      0.1552,
      0.2241,
      0.2414,
      0.5345,
      0.5517,
      0.7241,
      0.7586,
      0.7931,
      0.8621,
      1.0,
      0.931,
      0.8621,
      0.8966,
      0.6207,
      0.6034,
      0.3966,
      0.3103,
      0.2759,
      0.2069,
      0.1034,
      0.1034,
      0.1034,
      0.1379,
      0.1897,
      0.3621,
      0.4655,
      0.5345,
      0.5345,
      0.5345,
      0.5,
      0.569,
      0.6034,
      0.9138,
      0.8448,
      0.7069,
      0.6034,
      0.6552,
      0.6552,
      0.6552,
      0.7586,
      0.7241,
      0.6897,
      0.4828,
      0.5345,
      0.5,
      0.5345,
      0.431,
      0.431,
      0.6207,
      0.5172,
      0.6034,
      0.6034,
      0.431,
      0.4138
    ],
    "pressure_away": [
      0.0946,
      0.1892,
      0.3378,
      0.3378,
      0.4459,
      0.6486,
      0.9189,
      0.9189,
      0.9189,
      0.9189,
      0.8784,
      0.7838,
      0.6351,
      0.6622,
      0.5676,
      0.3649,
      0.0946,
      0.0946,
      0.0946,
      0.1892,
      0.2432,
      0.2432,
      0.3784,
      0.3784,
      0.3784,
      0.3919,
      0.4054,
      0.4189,
      0.4324,
      0.3378,
      0.2297,
      0.2297,
      0.0946,
      0.0811,
      0.0676,
      0.0541,
      0.1622,
      0.1486,
      0.1351,
      0.1351,
      0.2973,
      0.3108,
      0.3243,
      0.3649,
      0.3784,
      0.5405,
      0.5541,
      0.6216,
      0.6216,
      0.6216,
      0.5,
      0.527,
      0.5405,
      0.4865,
      0.473,
      0.3108,
      0.1757,
      0.1351,
      0.2432,
      0.5676,
      0.5946,
      0.5676,
      0.5405,
      0.5541,
      0.5811,
      0.6216,
      0.8243,
      0.7973,
      0.7162,
      0.4054,
      0.4054,
      0.473,
      0.5811,
      0.5676,
      0.5676,
      0.527,
      0.4865,
      0.6757,
      0.9189,
      0.9595,
      0.8919,
      1.0,
      0.9324,
      0.9324,
      0.973,
      0.973,
      0.8243,
      0.6757,
      0.4054,
      0.4595,
      0.473,
      0.3378
    ]
  },
  "shots": [
    {
      "x": 113.1,
      "y": 37.2,
      "xg": 0.1004,
      "goal": false,
      "team": "away",
      "player": "Ramírez",
      "player_full": "Héctor Rodas Ramírez",
      "minute": 3,
      "technique": "Volley",
      "body_part": "Right Foot",
      "period": 1,
      "is_penalty_shootout": false
    },
    {
      "x": 113.2,
      "y": 52.2,
      "xg": 0.1218,
      "goal": false,
      "team": "home",
      "player": "Krishna",
      "player_full": "Roy Krishna",
      "minute": 6,
      "technique": "Normal",
      "body_part": "Right Foot",
      "period": 1,
      "is_penalty_shootout": false
    },
    {
      "x": 99.8,
      "y": 49.2,
      "xg": 0.0823,
      "goal": false,
      "team": "away",
      "player": "González",
      "player_full": "Francisco Javier Hernández González",
      "minute": 9,
      "technique": "Normal",
      "body_part": "Right Foot",
      "period": 1,
      "is_penalty_shootout": false
    },
    {
      "x": 87.2,
      "y": 40.4,
      "xg": 0.0201,
      "goal": false,
      "team": "home",
      "player": "Colaco",
      "player_full": "Liston Colaco",
      "minute": 13,
      "technique": "Normal",
      "body_part": "Right Foot",
      "period": 1,
      "is_penalty_shootout": false
    },
    {
      "x": 112.3,
      "y": 37.0,
      "xg": 0.3636,
      "goal": false,
      "team": "home",
      "player": "Williams",
      "player_full": "David Joel Williams",
      "minute": 14,
      "technique": "Normal",
      "body_part": "Left Foot",
      "period": 1,
      "is_penalty_shootout": false
    },
    {
      "x": 103.6,
      "y": 15.7,
      "xg": 0.0082,
      "goal": false,
      "team": "home",
      "player": "Colaco",
      "player_full": "Liston Colaco",
      "minute": 14,
      "technique": "Normal",
      "body_part": "Right Foot",
      "period": 1,
      "is_penalty_shootout": false
    },
    {
      "x": 101.4,
      "y": 57.9,
      "xg": 0.0242,
      "goal": false,
      "team": "home",
      "player": "Singh",
      "player_full": "Manvir Singh",
      "minute": 18,
      "technique": "Normal",
      "body_part": "Left Foot",
      "period": 1,
      "is_penalty_shootout": false
    },
    {
      "x": 103.2,
      "y": 49.6,
      "xg": 0.0661,
      "goal": false,
      "team": "home",
      "player": "Williams",
      "player_full": "David Joel Williams",
      "minute": 19,
      "technique": "Normal",
      "body_part": "Right Foot",
      "period": 1,
      "is_penalty_shootout": false
    },
    {
      "x": 99.9,
      "y": 56.9,
      "xg": 0.0243,
      "goal": false,
      "team": "away",
      "player": "Mawihmingthanga",
      "player_full": "Jerry Mawihmingthanga",
      "minute": 20,
      "technique": "Normal",
      "body_part": "Right Foot",
      "period": 1,
      "is_penalty_shootout": false
    },
    {
      "x": 98.4,
      "y": 30.8,
      "xg": 0.0378,
      "goal": false,
      "team": "away",
      "player": "Sekar",
      "player_full": "Nandhakumar Sekar",
      "minute": 21,
      "technique": "Normal",
      "body_part": "Right Foot",
      "period": 1,
      "is_penalty_shootout": false
    },
    {
      "x": 84.7,
      "y": 44.9,
      "xg": 0.0092,
      "goal": false,
      "team": "away",
      "player": "Singh",
      "player_full": "Moirangthem Thoiba Singh",
      "minute": 23,
      "technique": "Volley",
      "body_part": "Right Foot",
      "period": 1,
      "is_penalty_shootout": false
    },
    {
      "x": 96.1,
      "y": 18.1,
      "xg": 0.0078,
      "goal": false,
      "team": "home",
      "player": "Colaco",
      "player_full": "Liston Colaco",
      "minute": 24,
      "technique": "Normal",
      "body_part": "Right Foot",
      "period": 1,
      "is_penalty_shootout": false
    },
    {
      "x": 100.6,
      "y": 37.1,
      "xg": 0.0601,
      "goal": false,
      "team": "home",
      "player": "Krishna",
      "player_full": "Roy Krishna",
      "minute": 25,
      "technique": "Normal",
      "body_part": "Right Foot",
      "period": 1,
      "is_penalty_shootout": false
    },
    {
      "x": 114.3,
      "y": 35.2,
      "xg": 0.1698,
      "goal": false,
      "team": "home",
      "player": "Krishna",
      "player_full": "Roy Krishna",
      "minute": 26,
      "technique": "Normal",
      "body_part": "Left Foot",
      "period": 1,
      "is_penalty_shootout": false
    },
    {
      "x": 94.8,
      "y": 25.1,
      "xg": 0.0179,
      "goal": false,
      "team": "home",
      "player": "Mehta",
      "player_full": "Ashutosh Mehta",
      "minute": 26,
      "technique": "Normal",
      "body_part": "Right Foot",
      "period": 1,
      "is_penalty_shootout": false
    },
    {
      "x": 111.1,
      "y": 29.6,
      "xg": 0.4058,
      "goal": false,
      "team": "home",
      "player": "Colaco",
      "player_full": "Liston Colaco",
      "minute": 28,
      "technique": "Normal",
      "body_part": "Left Foot",
      "period": 1,
      "is_penalty_shootout": false
    },
    {
      "x": 102.8,
      "y": 43.9,
      "xg": 0.1927,
      "goal": false,
      "team": "home",
      "player": "Krishna",
      "player_full": "Roy Krishna",
      "minute": 34,
      "technique": "Normal",
      "body_part": "Left Foot",
      "period": 1,
      "is_penalty_shootout": false
    },
    {
      "x": 87.8,
      "y": 37.4,
      "xg": 0.0233,
      "goal": false,
      "team": "home",
      "player": "Colaco",
      "player_full": "Liston Colaco",
      "minute": 38,
      "technique": "Normal",
      "body_part": "Right Foot",
      "period": 1,
      "is_penalty_shootout": false
    },
    {
      "x": 104.0,
      "y": 51.8,
      "xg": 0.046,
      "goal": false,
      "team": "home",
      "player": "Krishna",
      "player_full": "Roy Krishna",
      "minute": 38,
      "technique": "Volley",
      "body_part": "Right Foot",
      "period": 1,
      "is_penalty_shootout": false
    },
    {
      "x": 92.2,
      "y": 38.2,
      "xg": 0.0203,
      "goal": false,
      "team": "away",
      "player": "Mawihmingthanga",
      "player_full": "Jerry Mawihmingthanga",
      "minute": 45,
      "technique": "Half Volley",
      "body_part": "Right Foot",
      "period": 2,
      "is_penalty_shootout": false
    },
    {
      "x": 112.2,
      "y": 36.4,
      "xg": 0.2825,
      "goal": false,
      "team": "home",
      "player": "Williams",
      "player_full": "David Joel Williams",
      "minute": 50,
      "technique": "Diving Header",
      "body_part": "Head",
      "period": 2,
      "is_penalty_shootout": false
    },
    {
      "x": 93.5,
      "y": 50.9,
      "xg": 0.0472,
      "goal": false,
      "team": "away",
      "player": "González",
      "player_full": "Francisco Javier Hernández González",
      "minute": 54,
      "technique": "Normal",
      "body_part": "Left Foot",
      "period": 2,
      "is_penalty_shootout": false
    },
    {
      "x": 100.8,
      "y": 45.3,
      "xg": 0.0443,
      "goal": false,
      "team": "away",
      "player": "Mawihmingthanga",
      "player_full": "Jerry Mawihmingthanga",
      "minute": 55,
      "technique": "Overhead Kick",
      "body_part": "Right Foot",
      "period": 2,
      "is_penalty_shootout": false
    },
    {
      "x": 103.6,
      "y": 33.9,
      "xg": 0.145,
      "goal": false,
      "team": "away",
      "player": "Mawihmingthanga",
      "player_full": "Jerry Mawihmingthanga",
      "minute": 56,
      "technique": "Normal",
      "body_part": "Left Foot",
      "period": 2,
      "is_penalty_shootout": false
    },
    {
      "x": 99.7,
      "y": 27.0,
      "xg": 0.0286,
      "goal": false,
      "team": "away",
      "player": "Sekar",
      "player_full": "Nandhakumar Sekar",
      "minute": 66,
      "technique": "Normal",
      "body_part": "Right Foot",
      "period": 2,
      "is_penalty_shootout": false
    },
    {
      "x": 107.4,
      "y": 56.6,
      "xg": 0.0339,
      "goal": false,
      "team": "away",
      "player": "González",
      "player_full": "Francisco Javier Hernández González",
      "minute": 67,
      "technique": "Half Volley",
      "body_part": "Left Foot",
      "period": 2,
      "is_penalty_shootout": false
    },
    {
      "x": 78.4,
      "y": 39.9,
      "xg": 0.0052,
      "goal": false,
      "team": "home",
      "player": "Rodrigues",
      "player_full": "Lenny Rodrigues",
      "minute": 69,
      "technique": "Normal",
      "body_part": "Right Foot",
      "period": 2,
      "is_penalty_shootout": false
    },
    {
      "x": 107.8,
      "y": 27.2,
      "xg": 0.0419,
      "goal": false,
      "team": "away",
      "player": "Chhakchhuak",
      "player_full": "Isaac Vanmalsawma Chhakchhuak",
      "minute": 73,
      "technique": "Half Volley",
      "body_part": "Right Foot",
      "period": 2,
      "is_penalty_shootout": false
    },
    {
      "x": 108.2,
      "y": 48.9,
      "xg": 0.2275,
      "goal": false,
      "team": "home",
      "player": "Das",
      "player_full": "Prabir Das",
      "minute": 88,
      "technique": "Half Volley",
      "body_part": "Right Foot",
      "period": 2,
      "is_penalty_shootout": false
    },
    {
      "x": 96.5,
      "y": 43.5,
      "xg": 0.0289,
      "goal": false,
      "team": "away",
      "player": "Kumar",
      "player_full": "Nikhil Raj Murugesh Kumar",
      "minute": 91,
      "technique": "Half Volley",
      "body_part": "Right Foot",
      "period": 2,
      "is_penalty_shootout": false
    }
  ],
  "network_home": {
    "nodes": [
      {
        "id": "Pritam Kotal",
        "short": "Kotal",
        "x": 31.61,
        "y": 58.84,
        "size": 156.8,
        "is_playmaker": true,
        "betweenness": 0.2667,
        "eigenvector": 0.5117
      },
      {
        "id": "Carl Gerard McHugh",
        "short": "McHugh",
        "x": 47.89,
        "y": 41.18,
        "size": 131.3,
        "is_playmaker": false,
        "betweenness": 0.2444,
        "eigenvector": 0.5218
      },
      {
        "id": "Amrinder Singh",
        "short": "Singh",
        "x": 8.48,
        "y": 41.75,
        "size": 83.9,
        "is_playmaker": false,
        "betweenness": 0.0,
        "eigenvector": 0.1567
      },
      {
        "id": "José Luis Espinosa Arroyo",
        "short": "Arroyo",
        "x": 32.7,
        "y": 29.02,
        "size": 125.2,
        "is_playmaker": false,
        "betweenness": 0.0556,
        "eigenvector": 0.5114
      },
      {
        "id": "Deepak Tangri",
        "short": "Tangri",
        "x": 50.41,
        "y": 48.57,
        "size": 80.4,
        "is_playmaker": true,
        "betweenness": 0.2778,
        "eigenvector": 0.157
      },
      {
        "id": "David Joel Williams",
        "short": "Williams",
        "x": 71.6,
        "y": 35.03,
        "size": 70.8,
        "is_playmaker": false,
        "betweenness": 0.1111,
        "eigenvector": 0.1601
      },
      {
        "id": "Subhasish Bose",
        "short": "Bose",
        "x": 44.41,
        "y": 13.76,
        "size": 86.6,
        "is_playmaker": false,
        "betweenness": 0.0111,
        "eigenvector": 0.2528
      },
      {
        "id": "Manvir Singh",
        "short": "Singh",
        "x": 78.74,
        "y": 62.38,
        "size": 67.3,
        "is_playmaker": false,
        "betweenness": 0.0,
        "eigenvector": 0.148
      },
      {
        "id": "Ashutosh Mehta",
        "short": "Mehta",
        "x": 58.27,
        "y": 73.41,
        "size": 72.5,
        "is_playmaker": false,
        "betweenness": 0.0111,
        "eigenvector": 0.1097
      },
      {
        "id": "Liston Colaco",
        "short": "Colaco",
        "x": 79.38,
        "y": 8.09,
        "size": 71.7,
        "is_playmaker": false,
        "betweenness": 0.0,
        "eigenvector": 0.1776
      },
      {
        "id": "Roy Krishna",
        "short": "Krishna",
        "x": 69.22,
        "y": 41.25,
        "size": 58.5,
        "is_playmaker": false,
        "betweenness": 0.2,
        "eigenvector": 0.0097
      }
    ],
    "edges": [
      {
        "source": "Pritam Kotal",
        "target": "Carl Gerard McHugh",
        "weight": 19,
        "direction": "forward"
      },
      {
        "source": "Pritam Kotal",
        "target": "José Luis Espinosa Arroyo",
        "weight": 14,
        "direction": "lateral"
      },
      {
        "source": "Pritam Kotal",
        "target": "Deepak Tangri",
        "weight": 10,
        "direction": "forward"
      },
      {
        "source": "Pritam Kotal",
        "target": "Amrinder Singh",
        "weight": 10,
        "direction": "backward"
      },
      {
        "source": "Pritam Kotal",
        "target": "Ashutosh Mehta",
        "weight": 7,
        "direction": "forward"
      },
      {
        "source": "Carl Gerard McHugh",
        "target": "José Luis Espinosa Arroyo",
        "weight": 12,
        "direction": "backward"
      },
      {
        "source": "Carl Gerard McHugh",
        "target": "Pritam Kotal",
        "weight": 10,
        "direction": "backward"
      },
      {
        "source": "Carl Gerard McHugh",
        "target": "David Joel Williams",
        "weight": 10,
        "direction": "forward"
      },
      {
        "source": "Carl Gerard McHugh",
        "target": "Manvir Singh",
        "weight": 8,
        "direction": "forward"
      },
      {
        "source": "Carl Gerard McHugh",
        "target": "Subhasish Bose",
        "weight": 7,
        "direction": "lateral"
      },
      {
        "source": "Amrinder Singh",
        "target": "Pritam Kotal",
        "weight": 15,
        "direction": "forward"
      },
      {
        "source": "Amrinder Singh",
        "target": "José Luis Espinosa Arroyo",
        "weight": 8,
        "direction": "forward"
      },
      {
        "source": "José Luis Espinosa Arroyo",
        "target": "Pritam Kotal",
        "weight": 13,
        "direction": "lateral"
      },
      {
        "source": "José Luis Espinosa Arroyo",
        "target": "Carl Gerard McHugh",
        "weight": 10,
        "direction": "forward"
      },
      {
        "source": "José Luis Espinosa Arroyo",
        "target": "Subhasish Bose",
        "weight": 9,
        "direction": "forward"
      },
      {
        "source": "José Luis Espinosa Arroyo",
        "target": "Liston Colaco",
        "weight": 6,
        "direction": "forward"
      },
      {
        "source": "Deepak Tangri",
        "target": "Pritam Kotal",
        "weight": 11,
        "direction": "backward"
      },
      {
        "source": "Deepak Tangri",
        "target": "Carl Gerard McHugh",
        "weight": 6,
        "direction": "lateral"
      },
      {
        "source": "Deepak Tangri",
        "target": "Roy Krishna",
        "weight": 1,
        "direction": "forward"
      },
      {
        "source": "David Joel Williams",
        "target": "Liston Colaco",
        "weight": 6,
        "direction": "forward"
      },
      {
        "source": "David Joel Williams",
        "target": "Roy Krishna",
        "weight": 1,
        "direction": "lateral"
      },
      {
        "source": "Subhasish Bose",
        "target": "José Luis Espinosa Arroyo",
        "weight": 8,
        "direction": "backward"
      },
      {
        "source": "Subhasish Bose",
        "target": "Liston Colaco",
        "weight": 7,
        "direction": "forward"
      },
      {
        "source": "Subhasish Bose",
        "target": "Carl Gerard McHugh",
        "weight": 5,
        "direction": "lateral"
      },
      {
        "source": "Ashutosh Mehta",
        "target": "Pritam Kotal",
        "weight": 7,
        "direction": "backward"
      },
      {
        "source": "Ashutosh Mehta",
        "target": "Manvir Singh",
        "weight": 6,
        "direction": "forward"
      },
      {
        "source": "Roy Krishna",
        "target": "David Joel Williams",
        "weight": 1,
        "direction": "lateral"
      },
      {
        "source": "Roy Krishna",
        "target": "Deepak Tangri",
        "weight": 1,
        "direction": "backward"
      }
    ]
  },
  "network_away": {
    "nodes": [
      {
        "id": "Sahil Panwar",
        "short": "Panwar",
        "x": 48.31,
        "y": 8.53,
        "size": 115.8,
        "is_playmaker": false,
        "betweenness": 0.0,
        "eigenvector": 0.5469
      },
      {
        "id": "Víctor Mongil Adeva",
        "short": "Adeva",
        "x": 38.16,
        "y": 29.36,
        "size": 137.3,
        "is_playmaker": true,
        "betweenness": 0.3,
        "eigenvector": 0.518
      },
      {
        "id": "Liridon Krasniqi",
        "short": "Krasniqi",
        "x": 61.89,
        "y": 25.58,
        "size": 129.7,
        "is_playmaker": true,
        "betweenness": 0.4111,
        "eigenvector": 0.4192
      },
      {
        "id": "Isaac Vanmalsawma Chhakchhuak",
        "short": "Chhakchhuak",
        "x": 66.53,
        "y": 30.84,
        "size": 72.7,
        "is_playmaker": false,
        "betweenness": 0.0,
        "eigenvector": 0.2061
      },
      {
        "id": "Lalhrezuala Sailung",
        "short": "Sailung",
        "x": 52.39,
        "y": 73.58,
        "size": 82.8,
        "is_playmaker": false,
        "betweenness": 0.2778,
        "eigenvector": 0.0974
      },
      {
        "id": "Jerry Mawihmingthanga",
        "short": "Mawihmingth",
        "x": 67.62,
        "y": 69.43,
        "size": 87.9,
        "is_playmaker": false,
        "betweenness": 0.1889,
        "eigenvector": 0.2311
      },
      {
        "id": "Héctor Rodas Ramírez",
        "short": "Ramírez",
        "x": 41.66,
        "y": 55.45,
        "size": 80.3,
        "is_playmaker": false,
        "betweenness": 0.2667,
        "eigenvector": 0.2229
      },
      {
        "id": "Francisco Javier Hernández González",
        "short": "González",
        "x": 68.34,
        "y": 44.91,
        "size": 93.0,
        "is_playmaker": false,
        "betweenness": 0.1556,
        "eigenvector": 0.2469
      },
      {
        "id": "Arshdeep Singh Saini",
        "short": "Saini",
        "x": 10.81,
        "y": 42.58,
        "size": 68.9,
        "is_playmaker": false,
        "betweenness": 0.0,
        "eigenvector": 0.0
      },
      {
        "id": "Nandhakumar Sekar",
        "short": "Sekar",
        "x": 59.2,
        "y": 8.85,
        "size": 66.4,
        "is_playmaker": false,
        "betweenness": 0.0,
        "eigenvector": 0.0824
      },
      {
        "id": "Moirangthem Thoiba Singh",
        "short": "Singh",
        "x": 55.16,
        "y": 42.53,
        "size": 70.2,
        "is_playmaker": false,
        "betweenness": 0.0556,
        "eigenvector": 0.1843
      }
    ],
    "edges": [
      {
        "source": "Sahil Panwar",
        "target": "Víctor Mongil Adeva",
        "weight": 16,
        "direction": "backward"
      },
      {
        "source": "Sahil Panwar",
        "target": "Liridon Krasniqi",
        "weight": 5,
        "direction": "forward"
      },
      {
        "source": "Sahil Panwar",
        "target": "Francisco Javier Hernández González",
        "weight": 4,
        "direction": "forward"
      },
      {
        "source": "Víctor Mongil Adeva",
        "target": "Sahil Panwar",
        "weight": 15,
        "direction": "forward"
      },
      {
        "source": "Víctor Mongil Adeva",
        "target": "Héctor Rodas Ramírez",
        "weight": 8,
        "direction": "lateral"
      },
      {
        "source": "Víctor Mongil Adeva",
        "target": "Liridon Krasniqi",
        "weight": 8,
        "direction": "forward"
      },
      {
        "source": "Víctor Mongil Adeva",
        "target": "Moirangthem Thoiba Singh",
        "weight": 4,
        "direction": "forward"
      },
      {
        "source": "Liridon Krasniqi",
        "target": "Isaac Vanmalsawma Chhakchhuak",
        "weight": 10,
        "direction": "forward"
      },
      {
        "source": "Liridon Krasniqi",
        "target": "Sahil Panwar",
        "weight": 8,
        "direction": "backward"
      },
      {
        "source": "Liridon Krasniqi",
        "target": "Francisco Javier Hernández González",
        "weight": 5,
        "direction": "forward"
      },
      {
        "source": "Liridon Krasniqi",
        "target": "Jerry Mawihmingthanga",
        "weight": 5,
        "direction": "forward"
      },
      {
        "source": "Liridon Krasniqi",
        "target": "Nandhakumar Sekar",
        "weight": 4,
        "direction": "lateral"
      },
      {
        "source": "Liridon Krasniqi",
        "target": "Moirangthem Thoiba Singh",
        "weight": 4,
        "direction": "backward"
      },
      {
        "source": "Isaac Vanmalsawma Chhakchhuak",
        "target": "Lalhrezuala Sailung",
        "weight": 4,
        "direction": "backward"
      },
      {
        "source": "Lalhrezuala Sailung",
        "target": "Jerry Mawihmingthanga",
        "weight": 9,
        "direction": "forward"
      },
      {
        "source": "Lalhrezuala Sailung",
        "target": "Héctor Rodas Ramírez",
        "weight": 4,
        "direction": "backward"
      },
      {
        "source": "Jerry Mawihmingthanga",
        "target": "Lalhrezuala Sailung",
        "weight": 5,
        "direction": "backward"
      },
      {
        "source": "Héctor Rodas Ramírez",
        "target": "Víctor Mongil Adeva",
        "weight": 8,
        "direction": "lateral"
      },
      {
        "source": "Francisco Javier Hernández González",
        "target": "Jerry Mawihmingthanga",
        "weight": 7,
        "direction": "lateral"
      },
      {
        "source": "Francisco Javier Hernández González",
        "target": "Liridon Krasniqi",
        "weight": 5,
        "direction": "backward"
      },
      {
        "source": "Arshdeep Singh Saini",
        "target": "Víctor Mongil Adeva",
        "weight": 6,
        "direction": "forward"
      },
      {
        "source": "Arshdeep Singh Saini",
        "target": "Francisco Javier Hernández González",
        "weight": 5,
        "direction": "forward"
      },
      {
        "source": "Nandhakumar Sekar",
        "target": "Liridon Krasniqi",
        "weight": 5,
        "direction": "lateral"
      },
      {
        "source": "Moirangthem Thoiba Singh",
        "target": "Francisco Javier Hernández González",
        "weight": 4,
        "direction": "forward"
      }
    ]
  },
  "vaep": {
    "home": [
      {
        "player": "David Joel Williams",
        "short": "Williams",
        "vaep": 1.6613,
        "role": "Contributor",
        "n_actions": 138
      },
      {
        "player": "Manvir Singh",
        "short": "Singh",
        "vaep": 1.5365,
        "role": "Progressor",
        "n_actions": 124
      },
      {
        "player": "Liston Colaco",
        "short": "Colaco",
        "vaep": 1.2257,
        "role": "Contributor",
        "n_actions": 126
      },
      {
        "player": "Carl Gerard McHugh",
        "short": "McHugh",
        "vaep": 0.8864,
        "role": "Progressor",
        "n_actions": 225
      },
      {
        "player": "Roy Krishna",
        "short": "Krishna",
        "vaep": 0.6801,
        "role": "Contributor",
        "n_actions": 68
      }
    ],
    "away": [
      {
        "player": "Francisco Javier Hernández González",
        "short": "González",
        "vaep": 0.7998,
        "role": "Contributor",
        "n_actions": 132
      },
      {
        "player": "Jerry Mawihmingthanga",
        "short": "Mawihmingthanga",
        "vaep": 0.6338,
        "role": "Contributor",
        "n_actions": 124
      },
      {
        "player": "Isaac Vanmalsawma Chhakchhuak",
        "short": "Chhakchhuak",
        "vaep": 0.5849,
        "role": "Progressor",
        "n_actions": 123
      },
      {
        "player": "Liridon Krasniqi",
        "short": "Krasniqi",
        "vaep": 0.5498,
        "role": "Progressor",
        "n_actions": 149
      },
      {
        "player": "Nandhakumar Sekar",
        "short": "Sekar",
        "vaep": 0.3778,
        "role": "Contributor",
        "n_actions": 73
      }
    ]
  },
  "game_state": {},
  "insights": [
    "ATK Mohun Bagan created 1.40 more xG — dominant territorial control",
    "Even possession — contested midfield throughout"
  ]
}