[
  {
    "match_id": "FIN-20190804-HJK-MAR",
    "date": "2019-08-04",
    "home": "HJK",
    "away": "Mariehamn",
    "home_color": "#58a6ff",
    "away_color": "#58a6ff",
    "predicted": {
      "away_win": 0.1316,
      "draw": 0.2191,
      "home_win": 0.6493
    },
    "actual": {
      "home_goals": 2,
      "away_goals": 1,
      "outcome": "H"
    },
    "is_upset": false,
    "has_statsbomb": false,
    "statsbomb_match_id": null
  },
  {
    "match_id": "FIN-20190804-VPS-INT",
    "date": "2019-08-04",
    "home": "VPS",
    "away": "Inter Turku",
    "home_color": "#58a6ff",
    "away_color": "#010e80",
    "predicted": {
      "away_win": 0.381,
      "draw": 0.3783,
      "home_win": 0.2407
    },
    "actual": {
      "home_goals": 1,
      "away_goals": 2,
      "outcome": "A"
    },
    "is_upset": false,
    "has_statsbomb": false,
    "statsbomb_match_id": null
  },
  {
    "match_id": "FIN-20190805-HIF-MAR",
    "date": "2019-08-05",
    "home": "HIFK",
    "away": "Mariehamn",
    "home_color": "#58a6ff",
    "away_color": "#58a6ff",
    "predicted": {
      "away_win": 0.4461,
      "draw": 0.3467,
      "home_win": 0.2072
    },
    "actual": {
      "home_goals": 1,
      "away_goals": 1,
      "outcome": "D"
    },
    "is_upset": false,
    "has_statsbomb": false,
    "statsbomb_match_id": null
  },
  {
    "match_id": "FIN-20190815-SJK-MAR",
    "date": "2019-08-15",
    "home": "SJK",
    "away": "Mariehamn",
    "home_color": "#58a6ff",
    "away_color": "#58a6ff",
    "predicted": {
      "away_win": 0.3775,
      "draw": 0.3781,
      "home_win": 0.2444
    },
    "actual": {
      "home_goals": 0,
      "away_goals": 2,
      "outcome": "A"
    },
    "is_upset": false,
    "has_statsbomb": false,
    "statsbomb_match_id": null
  },
  {
    "match_id": "FIN-20190816-ILV-KUP",
    "date": "2019-08-16",
    "home": "Ilves",
    "away": "KuPS",
    "home_color": "#58a6ff",
    "away_color": "#58a6ff",
    "predicted": {
      "away_win": 0.3134,
      "draw": 0.3676,
      "home_win": 0.319
    },
    "actual": {
      "home_goals": 0,
      "away_goals": 2,
      "outcome": "A"
    },
    "is_upset": false,
    "has_statsbomb": false,
    "statsbomb_match_id": null
  },
  {
    "match_id": "FIN-20190816-INT-HIF",
    "date": "2019-08-16",
    "home": "Inter Turku",
    "away": "HIFK",
    "home_color": "#010e80",
    "away_color": "#58a6ff",
    "predicted": {
      "away_win": 0.2146,
      "draw": 0.3328,
      "home_win": 0.4526
    },
    "actual": {
      "home_goals": 3,
      "away_goals": 2,
      "outcome": "H"
    },
    "is_upset": false,
    "has_statsbomb": false,
    "statsbomb_match_id": null
  },
  {
    "match_id": "FIN-20190818-KPV-HJK",
    "date": "2019-08-18",
    "home": "KPV Kokkola",
    "away": "HJK",
    "home_color": "#58a6ff",
    "away_color": "#58a6ff",
    "predicted": {
      "away_win": 0.6264,
      "draw": 0.2496,
      "home_win": 0.124
    },
    "actual": {
      "home_goals": 2,
      "away_goals": 1,
      "outcome": "H"
    },
    "is_upset": true,
    "has_statsbomb": false,
    "statsbomb_match_id": null
  },
  {
    "match_id": "FIN-20190819-SJK-ROV",
    "date": "2019-08-19",
    "home": "SJK",
    "away": "Rovaniemi",
    "home_color": "#58a6ff",
    "away_color": "#58a6ff",
    "predicted": {
      "away_win": 0.2545,
      "draw": 0.3958,
      "home_win": 0.3497
    },
    "actual": {
      "home_goals": 0,
      "away_goals": 0,
      "outcome": "D"
    },
    "is_upset": false,
    "has_statsbomb": false,
    "statsbomb_match_id": null
  },
  {
    "match_id": "FIN-20190819-VPS-MAR",
    "date": "2019-08-19",
    "home": "VPS",
    "away": "Mariehamn",
    "home_color": "#58a6ff",
    "away_color": "#58a6ff",
    "predicted": {
      "away_win": 0.5543,
      "draw": 0.269,
      "home_win": 0.1767
    },
    "actual": {
      "home_goals": 2,
      "away_goals": 1,
      "outcome": "H"
    },
    "is_upset": true,
    "has_statsbomb": false,
    "statsbomb_match_id": null
  },
  {
    "match_id": "FIN-20190819-LAH-HON",
    "date": "2019-08-19",
    "home": "Lahti",
    "away": "Honka",
    "home_color": "#58a6ff",
    "away_color": "#58a6ff",
    "predicted": {
      "away_win": 0.5445,
      "draw": 0.3015,
      "home_win": 0.154
    },
    "actual": {
      "home_goals": 3,
      "away_goals": 2,
      "outcome": "H"
    },
    "is_upset": true,
    "has_statsbomb": false,
    "statsbomb_match_id": null
  },
  {
    "match_id": "FIN-20190823-HIF-ILV",
    "date": "2019-08-23",
    "home": "HIFK",
    "away": "Ilves",
    "home_color": "#58a6ff",
    "away_color": "#58a6ff",
    "predicted": {
      "away_win": 0.4752,
      "draw": 0.3346,
      "home_win": 0.1902
    },
    "actual": {
      "home_goals": 2,
      "away_goals": 2,
      "outcome": "D"
    },
    "is_upset": false,
    "has_statsbomb": false,
    "statsbomb_match_id": null
  },
  {
    "match_id": "FIN-20190824-KUP-VPS",
    "date": "2019-08-24",
    "home": "KuPS",
    "away": "VPS",
    "home_color": "#58a6ff",
    "away_color": "#58a6ff",
    "predicted": {
      "away_win": 0.1983,
      "draw": 0.2919,
      "home_win": 0.5098
    },
    "actual": {
      "home_goals": 5,
      "away_goals": 0,
      "outcome": "H"
    },
    "is_upset": false,
    "has_statsbomb": false,
    "statsbomb_match_id": null
  },
  {
    "match_id": "FIN-20190824-HON-HJK",
    "date": "2019-08-24",
    "home": "Honka",
    "away": "HJK",
    "home_color": "#58a6ff",
    "away_color": "#58a6ff",
    "predicted": {
      "away_win": 0.5031,
      "draw": 0.3276,
      "home_win": 0.1693
    },
    "actual": {
      "home_goals": 0,
      "away_goals": 1,
      "outcome": "A"
    },
    "is_upset": false,
    "has_statsbomb": false,
    "statsbomb_match_id": null
  },
  {
    "match_id": "FIN-20190825-MAR-SJK",
    "date": "2019-08-25",
    "home": "Mariehamn",
    "away": "SJK",
    "home_color": "#58a6ff",
    "away_color": "#58a6ff",
    "predicted": {
      "away_win": 0.2661,
      "draw": 0.3378,
      "home_win": 0.3961
    },
    "actual": {
      "home_goals": 1,
      "away_goals": 0,
      "outcome": "H"
    },
    "is_upset": false,
    "has_statsbomb": false,
    "statsbomb_match_id": null
  },
  {
    "match_id": "FIN-20190825-ROV-LAH",
    "date": "2019-08-25",
    "home": "Rovaniemi",
    "away": "Lahti",
    "home_color": "#58a6ff",
    "away_color": "#58a6ff",
    "predicted": {
      "away_win": 0.2722,
      "draw": 0.4074,
      "home_win": 0.3204
    },
    "actual": {
      "home_goals": 3,
      "away_goals": 0,
      "outcome": "H"
    },
    "is_upset": false,
    "has_statsbomb": false,
    "statsbomb_match_id": null
  },
  {
    "match_id": "FIN-20190826-INT-KPV",
    "date": "2019-08-26",
    "home": "Inter Turku",
    "away": "KPV Kokkola",
    "home_color": "#010e80",
    "away_color": "#58a6ff",
    "predicted": {
      "away_win": 0.1899,
      "draw": 0.2925,
      "home_win": 0.5176
    },
    "actual": {
      "home_goals": 2,
      "away_goals": 1,
      "outcome": "H"
    },
    "is_upset": false,
    "has_statsbomb": false,
    "statsbomb_match_id": null
  },
  {
    "match_id": "FIN-20190827-ILV-HIF",
    "date": "2019-08-27",
    "home": "Ilves",
    "away": "HIFK",
    "home_color": "#58a6ff",
    "away_color": "#58a6ff",
    "predicted": {
      "away_win": 0.234,
      "draw": 0.3519,
      "home_win": 0.4141
    },
    "actual": {
      "home_goals": 3,
      "away_goals": 1,
      "outcome": "H"
    },
    "is_upset": false,
    "has_statsbomb": false,
    "statsbomb_match_id": null
  },
  {
    "match_id": "FIN-20190831-SJK-KUP",
    "date": "2019-08-31",
    "home": "SJK",
    "away": "KuPS",
    "home_color": "#58a6ff",
    "away_color": "#58a6ff",
    "predicted": {
      "away_win": 0.4519,
      "draw": 0.343,
      "home_win": 0.205
    },
    "actual": {
      "home_goals": 1,
      "away_goals": 3,
      "outcome": "A"
    },
    "is_upset": false,
    "has_statsbomb": false,
    "statsbomb_match_id": null
  },
  {
    "match_id": "FIN-20190831-KPV-HON",
    "date": "2019-08-31",
    "home": "KPV Kokkola",
    "away": "Honka",
    "home_color": "#58a6ff",
    "away_color": "#58a6ff",
    "predicted": {
      "away_win": 0.5175,
      "draw": 0.3039,
      "home_win": 0.1786
    },
    "actual": {
      "home_goals": 0,
      "away_goals": 1,
      "outcome": "A"
    },
    "is_upset": false,
    "has_statsbomb": false,
    "statsbomb_match_id": null
  },
  {
    "match_id": "FIN-20190831-VPS-HIF",
    "date": "2019-08-31",
    "home": "VPS",
    "away": "HIFK",
    "home_color": "#58a6ff",
    "away_color": "#58a6ff",
    "predicted": {
      "away_win": 0.405,
      "draw": 0.336,
      "home_win": 0.259
    },
    "actual": {
      "home_goals": 3,
      "away_goals": 2,
      "outcome": "H"
    },
    "is_upset": true,
    "has_statsbomb": false,
    "statsbomb_match_id": null
  },
  {
    "match_id": "FIN-20190831-ILV-INT",
    "date": "2019-08-31",
    "home": "Ilves",
    "away": "Inter Turku",
    "home_color": "#58a6ff",
    "away_color": "#010e80",
    "predicted": {
      "away_win": 0.3172,
      "draw": 0.3858,
      "home_win": 0.297
    },
    "actual": {
      "home_goals": 0,
      "away_goals": 1,
      "outcome": "A"
    },
    "is_upset": false,
    "has_statsbomb": false,
    "statsbomb_match_id": null
  },
  {
    "match_id": "FIN-20190908-HIF-KPV",
    "date": "2019-09-08",
    "home": "HIFK",
    "away": "KPV Kokkola",
    "home_color": "#58a6ff",
    "away_color": "#58a6ff",
    "predicted": {
      "away_win": 0.2723,
      "draw": 0.3763,
      "home_win": 0.3514
    },
    "actual": {
      "home_goals": 3,
      "away_goals": 2,
      "outcome": "H"
    },
    "is_upset": false,
    "has_statsbomb": false,
    "statsbomb_match_id": null
  },
  {
    "match_id": "FIN-20190913-HIF-KPV",
    "date": "2019-09-13",
    "home": "HIFK",
    "away": "KPV Kokkola",
    "home_color": "#58a6ff",
    "away_color": "#58a6ff",
    "predicted": {
      "away_win": 0.3308,
      "draw": 0.3468,
      "home_win": 0.3224
    },
    "actual": {
      "home_goals": 3,
      "away_goals": 1,
      "outcome": "H"
    },
    "is_upset": false,
    "has_statsbomb": false,
    "statsbomb_match_id": null
  },
  {
    "match_id": "FIN-20190913-SJK-VPS",
    "date": "2019-09-13",
    "home": "SJK",
    "away": "VPS",
    "home_color": "#58a6ff",
    "away_color": "#58a6ff",
    "predicted": {
      "away_win": 0.2845,
      "draw": 0.3715,
      "home_win": 0.344
    },
    "actual": {
      "home_goals": 1,
      "away_goals": 1,
      "outcome": "D"
    },
    "is_upset": false,
    "has_statsbomb": false,
    "statsbomb_match_id": null
  },
  {
    "match_id": "FIN-20190914-LAH-ROV",
    "date": "2019-09-14",
    "home": "Lahti",
    "away": "Rovaniemi",
    "home_color": "#58a6ff",
    "away_color": "#58a6ff",
    "predicted": {
      "away_win": 0.3706,
      "draw": 0.4048,
      "home_win": 0.2245
    },
    "actual": {
      "home_goals": 3,
      "away_goals": 0,
      "outcome": "H"
    },
    "is_upset": true,
    "has_statsbomb": false,
    "statsbomb_match_id": null
  },
  {
    "match_id": "FIN-20190915-KUP-HJK",
    "date": "2019-09-15",
    "home": "KuPS",
    "away": "HJK",
    "home_color": "#58a6ff",
    "away_color": "#58a6ff",
    "predicted": {
      "away_win": 0.3596,
      "draw": 0.3831,
      "home_win": 0.2573
    },
    "actual": {
      "home_goals": 1,
      "away_goals": 0,
      "outcome": "H"
    },
    "is_upset": true,
    "has_statsbomb": false,
    "statsbomb_match_id": null
  },
  {
    "match_id": "FIN-20190915-INT-MAR",
    "date": "2019-09-15",
    "home": "Inter Turku",
    "away": "Mariehamn",
    "home_color": "#010e80",
    "away_color": "#58a6ff",
    "predicted": {
      "away_win": 0.2624,
      "draw": 0.3111,
      "home_win": 0.4265
    },
    "actual": {
      "home_goals": 2,
      "away_goals": 0,
      "outcome": "H"
    },
    "is_upset": false,
    "has_statsbomb": false,
    "statsbomb_match_id": null
  },
  {
    "match_id": "FIN-20190915-ILV-HON",
    "date": "2019-09-15",
    "home": "Ilves",
    "away": "Honka",
    "home_color": "#58a6ff",
    "away_color": "#58a6ff",
    "predicted": {
      "away_win": 0.3253,
      "draw": 0.3623,
      "home_win": 0.3124
    },
    "actual": {
      "home_goals": 0,
      "away_goals": 2,
      "outcome": "A"
    },
    "is_upset": false,
    "has_statsbomb": false,
    "statsbomb_match_id": null
  },
  {
    "match_id": "FIN-20190920-VPS-LAH",
    "date": "2019-09-20",
    "home": "VPS",
    "away": "Lahti",
    "home_color": "#58a6ff",
    "away_color": "#58a6ff",
    "predicted": {
      "away_win": 0.3506,
      "draw": 0.3486,
      "home_win": 0.3008
    },
    "actual": {
      "home_goals": 1,
      "away_goals": 2,
      "outcome": "A"
    },
    "is_upset": false,
    "has_statsbomb": false,
    "statsbomb_match_id": null
  },
  {
    "match_id": "FIN-20190921-HIF-SJK",
    "date": "2019-09-21",
    "home": "HIFK",
    "away": "SJK",
    "home_color": "#58a6ff",
    "away_color": "#58a6ff",
    "predicted": {
      "away_win": 0.3176,
      "draw": 0.3868,
      "home_win": 0.2956
    },
    "actual": {
      "home_goals": 2,
      "away_goals": 0,
      "outcome": "H"
    },
    "is_upset": true,
    "has_statsbomb": false,
    "statsbomb_match_id": null
  },
  {
    "match_id": "FIN-20190921-KPV-ROV",
    "date": "2019-09-21",
    "home": "KPV Kokkola",
    "away": "Rovaniemi",
    "home_color": "#58a6ff",
    "away_color": "#58a6ff",
    "predicted": {
      "away_win": 0.3542,
      "draw": 0.3466,
      "home_win": 0.2992
    },
    "actual": {
      "home_goals": 4,
      "away_goals": 1,
      "outcome": "H"
    },
    "is_upset": true,
    "has_statsbomb": false,
    "statsbomb_match_id": null
  },
  {
    "match_id": "FIN-20190921-HON-HJK",
    "date": "2019-09-21",
    "home": "Honka",
    "away": "HJK",
    "home_color": "#58a6ff",
    "away_color": "#58a6ff",
    "predicted": {
      "away_win": 0.3878,
      "draw": 0.3413,
      "home_win": 0.2709
    },
    "actual": {
      "home_goals": 3,
      "away_goals": 1,
      "outcome": "H"
    },
    "is_upset": true,
    "has_statsbomb": false,
    "statsbomb_match_id": null
  },
  {
    "match_id": "FIN-20190922-MAR-KUP",
    "date": "2019-09-22",
    "home": "Mariehamn",
    "away": "KuPS",
    "home_color": "#58a6ff",
    "away_color": "#58a6ff",
    "predicted": {
      "away_win": 0.5572,
      "draw": 0.274,
      "home_win": 0.1687
    },
    "actual": {
      "home_goals": 0,
      "away_goals": 1,
      "outcome": "A"
    },
    "is_upset": false,
    "has_statsbomb": false,
    "statsbomb_match_id": null
  },
  {
    "match_id": "FIN-20190922-ILV-INT",
    "date": "2019-09-22",
    "home": "Ilves",
    "away": "Inter Turku",
    "home_color": "#58a6ff",
    "away_color": "#010e80",
    "predicted": {
      "away_win": 0.3219,
      "draw": 0.3665,
      "home_win": 0.3115
    },
    "actual": {
      "home_goals": 1,
      "away_goals": 0,
      "outcome": "H"
    },
    "is_upset": false,
    "has_statsbomb": false,
    "statsbomb_match_id": null
  },
  {
    "match_id": "FIN-20190927-KUP-ILV",
    "date": "2019-09-27",
    "home": "KuPS",
    "away": "Ilves",
    "home_color": "#58a6ff",
    "away_color": "#58a6ff",
    "predicted": {
      "away_win": 0.2734,
      "draw": 0.3595,
      "home_win": 0.367
    },
    "actual": {
      "home_goals": 2,
      "away_goals": 0,
      "outcome": "H"
    },
    "is_upset": false,
    "has_statsbomb": false,
    "statsbomb_match_id": null
  },
  {
    "match_id": "FIN-20190927-SJK-KPV",
    "date": "2019-09-27",
    "home": "SJK",
    "away": "KPV Kokkola",
    "home_color": "#58a6ff",
    "away_color": "#58a6ff",
    "predicted": {
      "away_win": 0.3213,
      "draw": 0.347,
      "home_win": 0.3316
    },
    "actual": {
      "home_goals": 0,
      "away_goals": 2,
      "outcome": "A"
    },
    "is_upset": false,
    "has_statsbomb": false,
    "statsbomb_match_id": null
  },
  {
    "match_id": "FIN-20190928-HJK-MAR",
    "date": "2019-09-28",
    "home": "HJK",
    "away": "Mariehamn",
    "home_color": "#58a6ff",
    "away_color": "#58a6ff",
    "predicted": {
      "away_win": 0.2206,
      "draw": 0.319,
      "home_win": 0.4605
    },
    "actual": {
      "home_goals": 3,
      "away_goals": 0,
      "outcome": "H"
    },
    "is_upset": false,
    "has_statsbomb": false,
    "statsbomb_match_id": null
  },
  {
    "match_id": "FIN-20190928-ROV-VPS",
    "date": "2019-09-28",
    "home": "Rovaniemi",
    "away": "VPS",
    "home_color": "#58a6ff",
    "away_color": "#58a6ff",
    "predicted": {
      "away_win": 0.2672,
      "draw": 0.3275,
      "home_win": 0.4053
    },
    "actual": {
      "home_goals": 2,
      "away_goals": 1,
      "outcome": "H"
    },
    "is_upset": false,
    "has_statsbomb": false,
    "statsbomb_match_id": null
  },
  {
    "match_id": "FIN-20190928-INT-HON",
    "date": "2019-09-28",
    "home": "Inter Turku",
    "away": "Honka",
    "home_color": "#010e80",
    "away_color": "#58a6ff",
    "predicted": {
      "away_win": 0.3672,
      "draw": 0.3531,
      "home_win": 0.2796
    },
    "actual": {
      "home_goals": 0,
      "away_goals": 1,
      "outcome": "A"
    },
    "is_upset": false,
    "has_statsbomb": false,
    "statsbomb_match_id": null
  },
  {
    "match_id": "FIN-20190928-LAH-HIF",
    "date": "2019-09-28",
    "home": "Lahti",
    "away": "HIFK",
    "home_color": "#58a6ff",
    "away_color": "#58a6ff",
    "predicted": {
      "away_win": 0.3359,
      "draw": 0.4375,
      "home_win": 0.2266
    },
    "actual": {
      "home_goals": 2,
      "away_goals": 2,
      "outcome": "D"
    },
    "is_upset": false,
    "has_statsbomb": false,
    "statsbomb_match_id": null
  },
  {
    "match_id": "FIN-20191008-KUP-INT",
    "date": "2019-10-08",
    "home": "KuPS",
    "away": "Inter Turku",
    "home_color": "#58a6ff",
    "away_color": "#010e80",
    "predicted": {
      "away_win": 0.3746,
      "draw": 0.3454,
      "home_win": 0.28
    },
    "actual": {
      "home_goals": 2,
      "away_goals": 0,
      "outcome": "H"
    },
    "is_upset": true,
    "has_statsbomb": false,
    "statsbomb_match_id": null
  },
  {
    "match_id": "FIN-20191008-HON-SJK",
    "date": "2019-10-08",
    "home": "Honka",
    "away": "SJK",
    "home_color": "#58a6ff",
    "away_color": "#58a6ff",
    "predicted": {
      "away_win": 0.2217,
      "draw": 0.3299,
      "home_win": 0.4483
    },
    "actual": {
      "home_goals": 0,
      "away_goals": 0,
      "outcome": "D"
    },
    "is_upset": false,
    "has_statsbomb": false,
    "statsbomb_match_id": null
  },
  {
    "match_id": "FIN-20191008-HJK-LAH",
    "date": "2019-10-08",
    "home": "HJK",
    "away": "Lahti",
    "home_color": "#58a6ff",
    "away_color": "#58a6ff",
    "predicted": {
      "away_win": 0.1167,
      "draw": 0.2852,
      "home_win": 0.5981
    },
    "actual": {
      "home_goals": 4,
      "away_goals": 0,
      "outcome": "H"
    },
    "is_upset": false,
    "has_statsbomb": false,
    "statsbomb_match_id": null
  },
  {
    "match_id": "FIN-20191019-INT-KUP",
    "date": "2019-10-19",
    "home": "Inter Turku",
    "away": "KuPS",
    "home_color": "#010e80",
    "away_color": "#58a6ff",
    "predicted": {
      "away_win": 0.3902,
      "draw": 0.327,
      "home_win": 0.2828
    },
    "actual": {
      "home_goals": 0,
      "away_goals": 2,
      "outcome": "A"
    },
    "is_upset": false,
    "has_statsbomb": false,
    "statsbomb_match_id": null
  },
  {
    "match_id": "FIN-20191019-KPV-VPS",
    "date": "2019-10-19",
    "home": "KPV Kokkola",
    "away": "VPS",
    "home_color": "#58a6ff",
    "away_color": "#58a6ff",
    "predicted": {
      "away_win": 0.3069,
      "draw": 0.3369,
      "home_win": 0.3562
    },
    "actual": {
      "home_goals": 2,
      "away_goals": 3,
      "outcome": "A"
    },
    "is_upset": false,
    "has_statsbomb": false,
    "statsbomb_match_id": null
  },
  {
    "match_id": "FIN-20191019-ILV-HJK",
    "date": "2019-10-19",
    "home": "Ilves",
    "away": "HJK",
    "home_color": "#58a6ff",
    "away_color": "#58a6ff",
    "predicted": {
      "away_win": 0.3426,
      "draw": 0.3507,
      "home_win": 0.3067
    },
    "actual": {
      "home_goals": 2,
      "away_goals": 1,
      "outcome": "H"
    },
    "is_upset": false,
    "has_statsbomb": false,
    "statsbomb_match_id": null
  },
  {
    "match_id": "FIN-20191019-SJK-LAH",
    "date": "2019-10-19",
    "home": "SJK",
    "away": "Lahti",
    "home_color": "#58a6ff",
    "away_color": "#58a6ff",
    "predicted": {
      "away_win": 0.2927,
      "draw": 0.3363,
      "home_win": 0.3709
    },
    "actual": {
      "home_goals": 0,
      "away_goals": 0,
      "outcome": "D"
    },
    "is_upset": false,
    "has_statsbomb": false,
    "statsbomb_match_id": null
  },
  {
    "match_id": "FIN-20191019-HON-MAR",
    "date": "2019-10-19",
    "home": "Honka",
    "away": "Mariehamn",
    "home_color": "#58a6ff",
    "away_color": "#58a6ff",
    "predicted": {
      "away_win": 0.2069,
      "draw": 0.2922,
      "home_win": 0.5009
    },
    "actual": {
      "home_goals": 3,
      "away_goals": 0,
      "outcome": "H"
    },
    "is_upset": false,
    "has_statsbomb": false,
    "statsbomb_match_id": null
  },
  {
    "match_id": "FIN-20191019-HIF-ROV",
    "date": "2019-10-19",
    "home": "HIFK",
    "away": "Rovaniemi",
    "home_color": "#58a6ff",
    "away_color": "#58a6ff",
    "predicted": {
      "away_win": 0.271,
      "draw": 0.3262,
      "home_win": 0.4028
    },
    "actual": {
      "home_goals": 2,
      "away_goals": 0,
      "outcome": "H"
    },
    "is_upset": false,
    "has_statsbomb": false,
    "statsbomb_match_id": null
  },
  {
    "match_id": "FIN-20191023-HJK-LAH",
    "date": "2019-10-23",
    "home": "HJK",
    "away": "Lahti",
    "home_color": "#58a6ff",
    "away_color": "#58a6ff",
    "predicted": {
      "away_win": 0.1268,
      "draw": 0.2947,
      "home_win": 0.5786
    },
    "actual": {
      "home_goals": 2,
      "away_goals": 2,
      "outcome": "D"
    },
    "is_upset": true,
    "has_statsbomb": false,
    "statsbomb_match_id": null
  },
  {
    "match_id": "FIN-20191023-MAR-HIF",
    "date": "2019-10-23",
    "home": "Mariehamn",
    "away": "HIFK",
    "home_color": "#58a6ff",
    "away_color": "#58a6ff",
    "predicted": {
      "away_win": 0.2915,
      "draw": 0.3792,
      "home_win": 0.3293
    },
    "actual": {
      "home_goals": 0,
      "away_goals": 0,
      "outcome": "D"
    },
    "is_upset": false,
    "has_statsbomb": false,
    "statsbomb_match_id": null
  },
  {
    "match_id": "FIN-20191024-TPS-KPV",
    "date": "2019-10-24",
    "home": "TPS",
    "away": "KPV Kokkola",
    "home_color": "#58a6ff",
    "away_color": "#58a6ff",
    "predicted": {
      "away_win": 0.3675,
      "draw": 0.3956,
      "home_win": 0.2368
    },
    "actual": {
      "home_goals": 0,
      "away_goals": 0,
      "outcome": "D"
    },
    "is_upset": false,
    "has_statsbomb": false,
    "statsbomb_match_id": null
  },
  {
    "match_id": "FIN-20191027-KPV-TPS",
    "date": "2019-10-27",
    "home": "KPV Kokkola",
    "away": "TPS",
    "home_color": "#58a6ff",
    "away_color": "#58a6ff",
    "predicted": {
      "away_win": 0.3089,
      "draw": 0.3657,
      "home_win": 0.3254
    },
    "actual": {
      "home_goals": 0,
      "away_goals": 3,
      "outcome": "A"
    },
    "is_upset": false,
    "has_statsbomb": false,
    "statsbomb_match_id": null
  },
  {
    "match_id": "FIN-20191027-HJK-MAR",
    "date": "2019-10-27",
    "home": "HJK",
    "away": "Mariehamn",
    "home_color": "#58a6ff",
    "away_color": "#58a6ff",
    "predicted": {
      "away_win": 0.2352,
      "draw": 0.3181,
      "home_win": 0.4467
    },
    "actual": {
      "home_goals": 1,
      "away_goals": 1,
      "outcome": "D"
    },
    "is_upset": false,
    "has_statsbomb": false,
    "statsbomb_match_id": null
  },
  {
    "match_id": "FIN-20191030-MAR-HON",
    "date": "2019-10-30",
    "home": "Mariehamn",
    "away": "Honka",
    "home_color": "#58a6ff",
    "away_color": "#58a6ff",
    "predicted": {
      "away_win": 0.4044,
      "draw": 0.3811,
      "home_win": 0.2145
    },
    "actual": {
      "home_goals": 1,
      "away_goals": 2,
      "outcome": "A"
    },
    "is_upset": false,
    "has_statsbomb": false,
    "statsbomb_match_id": null
  },
  {
    "match_id": "FIN-20191105-KPV-LAH",
    "date": "2019-11-05",
    "home": "KPV Kokkola",
    "away": "Lahti",
    "home_color": "#58a6ff",
    "away_color": "#58a6ff",
    "predicted": {
      "away_win": 0.3712,
      "draw": 0.3806,
      "home_win": 0.2482
    },
    "actual": {
      "home_goals": 0,
      "away_goals": 0,
      "outcome": "D"
    },
    "is_upset": false,
    "has_statsbomb": false,
    "statsbomb_match_id": null
  },
  {
    "match_id": "FIN-20191105-HON-VPS",
    "date": "2019-11-05",
    "home": "Honka",
    "away": "VPS",
    "home_color": "#58a6ff",
    "away_color": "#58a6ff",
    "predicted": {
      "away_win": 0.2344,
      "draw": 0.3279,
      "home_win": 0.4377
    },
    "actual": {
      "home_goals": 1,
      "away_goals": 1,
      "outcome": "D"
    },
    "is_upset": false,
    "has_statsbomb": false,
    "statsbomb_match_id": null
  },
  {
    "match_id": "FIN-20191105-HJK-SJK",
    "date": "2019-11-05",
    "home": "HJK",
    "away": "SJK",
    "home_color": "#58a6ff",
    "away_color": "#58a6ff",
    "predicted": {
      "away_win": 0.2301,
      "draw": 0.3493,
      "home_win": 0.4207
    },
    "actual": {
      "home_goals": 2,
      "away_goals": 2,
      "outcome": "D"
    },
    "is_upset": false,
    "has_statsbomb": false,
    "statsbomb_match_id": null
  },
  {
    "match_id": "FIN-20191108-MAR-ILV",
    "date": "2019-11-08",
    "home": "Mariehamn",
    "away": "Ilves",
    "home_color": "#58a6ff",
    "away_color": "#58a6ff",
    "predicted": {
      "away_win": 0.4195,
      "draw": 0.3537,
      "home_win": 0.2268
    },
    "actual": {
      "home_goals": 0,
      "away_goals": 1,
      "outcome": "A"
    },
    "is_upset": false,
    "has_statsbomb": false,
    "statsbomb_match_id": null
  },
  {
    "match_id": "FIN-20191108-ROV-VPS",
    "date": "2019-11-08",
    "home": "Rovaniemi",
    "away": "VPS",
    "home_color": "#58a6ff",
    "away_color": "#58a6ff",
    "predicted": {
      "away_win": 0.2694,
      "draw": 0.3927,
      "home_win": 0.3379
    },
    "actual": {
      "home_goals": 2,
      "away_goals": 1,
      "outcome": "H"
    },
    "is_upset": false,
    "has_statsbomb": false,
    "statsbomb_match_id": null
  },
  {
    "match_id": "FIN-20191205-MAR-INT",
    "date": "2019-12-05",
    "home": "Mariehamn",
    "away": "Inter Turku",
    "home_color": "#58a6ff",
    "away_color": "#010e80",
    "predicted": {
      "away_win": 0.3763,
      "draw": 0.3548,
      "home_win": 0.269
    },
    "actual": {
      "home_goals": 1,
      "away_goals": 2,
      "outcome": "A"
    },
    "is_upset": false,
    "has_statsbomb": false,
    "statsbomb_match_id": null
  },
  {
    "match_id": "FIN-20191205-HIF-KUP",
    "date": "2019-12-05",
    "home": "HIFK",
    "away": "KuPS",
    "home_color": "#58a6ff",
    "away_color": "#58a6ff",
    "predicted": {
      "away_win": 0.5168,
      "draw": 0.3214,
      "home_win": 0.1618
    },
    "actual": {
      "home_goals": 1,
      "away_goals": 1,
      "outcome": "D"
    },
    "is_upset": false,
    "has_statsbomb": false,
    "statsbomb_match_id": null
  },
  {
    "match_id": "FIN-20191205-ROV-ILV",
    "date": "2019-12-05",
    "home": "Rovaniemi",
    "away": "Ilves",
    "home_color": "#58a6ff",
    "away_color": "#58a6ff",
    "predicted": {
      "away_win": 0.4149,
      "draw": 0.4161,
      "home_win": 0.169
    },
    "actual": {
      "home_goals": 0,
      "away_goals": 1,
      "outcome": "A"
    },
    "is_upset": false,
    "has_statsbomb": false,
    "statsbomb_match_id": null
  },
  {
    "match_id": "FIN-20200107-LAH-HJK",
    "date": "2020-01-07",
    "home": "Lahti",
    "away": "HJK",
    "home_color": "#58a6ff",
    "away_color": "#58a6ff",
    "predicted": {
      "away_win": 0.6972,
      "draw": 0.2122,
      "home_win": 0.0907
    },
    "actual": {
      "home_goals": 0,
      "away_goals": 4,
      "outcome": "A"
    },
    "is_upset": false,
    "has_statsbomb": false,
    "statsbomb_match_id": null
  },
  {
    "match_id": "FIN-20200107-HIF-KUP",
    "date": "2020-01-07",
    "home": "HIFK",
    "away": "KuPS",
    "home_color": "#58a6ff",
    "away_color": "#58a6ff",
    "predicted": {
      "away_win": 0.522,
      "draw": 0.3169,
      "home_win": 0.1611
    },
    "actual": {
      "home_goals": 0,
      "away_goals": 3,
      "outcome": "A"
    },
    "is_upset": false,
    "has_statsbomb": false,
    "statsbomb_match_id": null
  },
  {
    "match_id": "FIN-20200107-HAK-HON",
    "date": "2020-01-07",
    "home": "Haka",
    "away": "Honka",
    "home_color": "#58a6ff",
    "away_color": "#58a6ff",
    "predicted": {
      "away_win": 0.4354,
      "draw": 0.3819,
      "home_win": 0.1827
    },
    "actual": {
      "home_goals": 1,
      "away_goals": 1,
      "outcome": "D"
    },
    "is_upset": false,
    "has_statsbomb": false,
    "statsbomb_match_id": null
  },
  {
    "match_id": "FIN-20200107-SJK-TPS",
    "date": "2020-01-07",
    "home": "SJK",
    "away": "TPS",
    "home_color": "#58a6ff",
    "away_color": "#58a6ff",
    "predicted": {
      "away_win": 0.3361,
      "draw": 0.3623,
      "home_win": 0.3016
    },
    "actual": {
      "home_goals": 1,
      "away_goals": 0,
      "outcome": "H"
    },
    "is_upset": false,
    "has_statsbomb": false,
    "statsbomb_match_id": null
  },
  {
    "match_id": "FIN-20200107-ILV-MAR",
    "date": "2020-01-07",
    "home": "Ilves",
    "away": "Mariehamn",
    "home_color": "#58a6ff",
    "away_color": "#58a6ff",
    "predicted": {
      "away_win": 0.2001,
      "draw": 0.3216,
      "home_win": 0.4782
    },
    "actual": {
      "home_goals": 4,
      "away_goals": 3,
      "outcome": "H"
    },
    "is_upset": false,
    "has_statsbomb": false,
    "statsbomb_match_id": null
  },
  {
    "match_id": "FIN-20200108-SJK-HAK",
    "date": "2020-01-08",
    "home": "SJK",
    "away": "Haka",
    "home_color": "#58a6ff",
    "away_color": "#58a6ff",
    "predicted": {
      "away_win": 0.3087,
      "draw": 0.3525,
      "home_win": 0.3388
    },
    "actual": {
      "home_goals": 1,
      "away_goals": 1,
      "outcome": "D"
    },
    "is_upset": false,
    "has_statsbomb": false,
    "statsbomb_match_id": null
  },
  {
    "match_id": "FIN-20200108-INT-MAR",
    "date": "2020-01-08",
    "home": "Inter Turku",
    "away": "Mariehamn",
    "home_color": "#010e80",
    "away_color": "#58a6ff",
    "predicted": {
      "away_win": 0.1851,
      "draw": 0.2249,
      "home_win": 0.59
    },
    "actual": {
      "home_goals": 2,
      "away_goals": 1,
      "outcome": "H"
    },
    "is_upset": false,
    "has_statsbomb": false,
    "statsbomb_match_id": null
  },
  {
    "match_id": "FIN-20200108-ILV-HIF",
    "date": "2020-01-08",
    "home": "Ilves",
    "away": "HIFK",
    "home_color": "#58a6ff",
    "away_color": "#58a6ff",
    "predicted": {
      "away_win": 0.2986,
      "draw": 0.37,
      "home_win": 0.3315
    },
    "actual": {
      "home_goals": 2,
      "away_goals": 2,
      "outcome": "D"
    },
    "is_upset": false,
    "has_statsbomb": false,
    "statsbomb_match_id": null
  },
  {
    "match_id": "FIN-20200108-HJK-KUP",
    "date": "2020-01-08",
    "home": "HJK",
    "away": "KuPS",
    "home_color": "#58a6ff",
    "away_color": "#58a6ff",
    "predicted": {
      "away_win": 0.2316,
      "draw": 0.3423,
      "home_win": 0.4261
    },
    "actual": {
      "home_goals": 2,
      "away_goals": 2,
      "outcome": "D"
    },
    "is_upset": false,
    "has_statsbomb": false,
    "statsbomb_match_id": null
  },
  {
    "match_id": "FIN-20200108-ROV-TPS",
    "date": "2020-01-08",
    "home": "Rovaniemi",
    "away": "TPS",
    "home_color": "#58a6ff",
    "away_color": "#58a6ff",
    "predicted": {
      "away_win": 0.4084,
      "draw": 0.3658,
      "home_win": 0.2258
    },
    "actual": {
      "home_goals": 2,
      "away_goals": 3,
      "outcome": "A"
    },
    "is_upset": false,
    "has_statsbomb": false,
    "statsbomb_match_id": null
  },
  {
    "match_id": "FIN-20200109-HON-HIF",
    "date": "2020-01-09",
    "home": "Honka",
    "away": "HIFK",
    "home_color": "#58a6ff",
    "away_color": "#58a6ff",
    "predicted": {
      "away_win": 0.2198,
      "draw": 0.3472,
      "home_win": 0.4331
    },
    "actual": {
      "home_goals": 0,
      "away_goals": 1,
      "outcome": "A"
    },
    "is_upset": true,
    "has_statsbomb": false,
    "statsbomb_match_id": null
  },
  {
    "match_id": "FIN-20200109-HAK-ILV",
    "date": "2020-01-09",
    "home": "Haka",
    "away": "Ilves",
    "home_color": "#58a6ff",
    "away_color": "#58a6ff",
    "predicted": {
      "away_win": 0.4985,
      "draw": 0.3138,
      "home_win": 0.1878
    },
    "actual": {
      "home_goals": 0,
      "away_goals": 2,
      "outcome": "A"
    },
    "is_upset": false,
    "has_statsbomb": false,
    "statsbomb_match_id": null
  },
  {
    "match_id": "FIN-20200111-MAR-HJK",
    "date": "2020-01-11",
    "home": "Mariehamn",
    "away": "HJK",
    "home_color": "#58a6ff",
    "away_color": "#58a6ff",
    "predicted": {
      "away_win": 0.7773,
      "draw": 0.1389,
      "home_win": 0.0838
    },
    "actual": {
      "home_goals": 0,
      "away_goals": 5,
      "outcome": "A"
    },
    "is_upset": false,
    "has_statsbomb": false,
    "statsbomb_match_id": null
  },
  {
    "match_id": "FIN-20200207-INT-ROV",
    "date": "2020-02-07",
    "home": "Inter Turku",
    "away": "Rovaniemi",
    "home_color": "#010e80",
    "away_color": "#58a6ff",
    "predicted": {
      "away_win": 0.1634,
      "draw": 0.2786,
      "home_win": 0.5579
    },
    "actual": {
      "home_goals": 3,
      "away_goals": 1,
      "outcome": "H"
    },
    "is_upset": false,
    "has_statsbomb": false,
    "statsbomb_match_id": null
  },
  {
    "match_id": "FIN-20200210-HIF-HON",
    "date": "2020-02-10",
    "home": "HIFK",
    "away": "Honka",
    "home_color": "#58a6ff",
    "away_color": "#58a6ff",
    "predicted": {
      "away_win": 0.5401,
      "draw": 0.3021,
      "home_win": 0.1577
    },
    "actual": {
      "home_goals": 1,
      "away_goals": 1,
      "outcome": "D"
    },
    "is_upset": false,
    "has_statsbomb": false,
    "statsbomb_match_id": null
  },
  {
    "match_id": "FIN-20200210-LAH-MAR",
    "date": "2020-02-10",
    "home": "Lahti",
    "away": "Mariehamn",
    "home_color": "#58a6ff",
    "away_color": "#58a6ff",
    "predicted": {
      "away_win": 0.2954,
      "draw": 0.345,
      "home_win": 0.3596
    },
    "actual": {
      "home_goals": 3,
      "away_goals": 1,
      "outcome": "H"
    },
    "is_upset": false,
    "has_statsbomb": false,
    "statsbomb_match_id": null
  },
  {
    "match_id": "FIN-20200308-LAH-HON",
    "date": "2020-03-08",
    "home": "Lahti",
    "away": "Honka",
    "home_color": "#58a6ff",
    "away_color": "#58a6ff",
    "predicted": {
      "away_win": 0.5426,
      "draw": 0.2994,
      "home_win": 0.158
    },
    "actual": {
      "home_goals": 0,
      "away_goals": 0,
      "outcome": "D"
    },
    "is_upset": true,
    "has_statsbomb": false,
    "statsbomb_match_id": null
  },
  {
    "match_id": "FIN-20200411-TPS-KUP",
    "date": "2020-04-11",
    "home": "TPS",
    "away": "KuPS",
    "home_color": "#58a6ff",
    "away_color": "#58a6ff",
    "predicted": {
      "away_win": 0.5666,
      "draw": 0.261,
      "home_win": 0.1724
    },
    "actual": {
      "home_goals": 3,
      "away_goals": 2,
      "outcome": "H"
    },
    "is_upset": true,
    "has_statsbomb": false,
    "statsbomb_match_id": null
  },
  {
    "match_id": "FIN-20200411-ROV-SJK",
    "date": "2020-04-11",
    "home": "Rovaniemi",
    "away": "SJK",
    "home_color": "#58a6ff",
    "away_color": "#58a6ff",
    "predicted": {
      "away_win": 0.6177,
      "draw": 0.2488,
      "home_win": 0.1335
    },
    "actual": {
      "home_goals": 2,
      "away_goals": 3,
      "outcome": "A"
    },
    "is_upset": false,
    "has_statsbomb": false,
    "statsbomb_match_id": null
  },
  {
    "match_id": "FIN-20200411-HJK-INT",
    "date": "2020-04-11",
    "home": "HJK",
    "away": "Inter Turku",
    "home_color": "#58a6ff",
    "away_color": "#010e80",
    "predicted": {
      "away_win": 0.2622,
      "draw": 0.3474,
      "home_win": 0.3904
    },
    "actual": {
      "home_goals": 1,
      "away_goals": 1,
      "outcome": "D"
    },
    "is_upset": false,
    "has_statsbomb": false,
    "statsbomb_match_id": null
  },
  {
    "match_id": "FIN-20200411-ILV-HON",
    "date": "2020-04-11",
    "home": "Ilves",
    "away": "Honka",
    "home_color": "#58a6ff",
    "away_color": "#58a6ff",
    "predicted": {
      "away_win": 0.4835,
      "draw": 0.2906,
      "home_win": 0.2259
    },
    "actual": {
      "home_goals": 4,
      "away_goals": 1,
      "outcome": "H"
    },
    "is_upset": true,
    "has_statsbomb": false,
    "statsbomb_match_id": null
  },
  {
    "match_id": "FIN-20200411-LAH-HIF",
    "date": "2020-04-11",
    "home": "Lahti",
    "away": "HIFK",
    "home_color": "#58a6ff",
    "away_color": "#58a6ff",
    "predicted": {
      "away_win": 0.3046,
      "draw": 0.3579,
      "home_win": 0.3375
    },
    "actual": {
      "home_goals": 2,
      "away_goals": 1,
      "outcome": "H"
    },
    "is_upset": false,
    "has_statsbomb": false,
    "statsbomb_match_id": null
  },
  {
    "match_id": "FIN-20200411-HAK-MAR",
    "date": "2020-04-11",
    "home": "Haka",
    "away": "Mariehamn",
    "home_color": "#58a6ff",
    "away_color": "#58a6ff",
    "predicted": {
      "away_win": 0.4738,
      "draw": 0.3105,
      "home_win": 0.2157
    },
    "actual": {
      "home_goals": 0,
      "away_goals": 1,
      "outcome": "A"
    },
    "is_upset": false,
    "has_statsbomb": false,
    "statsbomb_match_id": null
  },
  {
    "match_id": "FIN-20200508-HAK-HIF",
    "date": "2020-05-08",
    "home": "Haka",
    "away": "HIFK",
    "home_color": "#58a6ff",
    "away_color": "#58a6ff",
    "predicted": {
      "away_win": 0.3893,
      "draw": 0.33,
      "home_win": 0.2808
    },
    "actual": {
      "home_goals": 0,
      "away_goals": 2,
      "outcome": "A"
    },
    "is_upset": false,
    "has_statsbomb": false,
    "statsbomb_match_id": null
  },
  {
    "match_id": "FIN-20200508-SJK-KUP",
    "date": "2020-05-08",
    "home": "SJK",
    "away": "KuPS",
    "home_color": "#58a6ff",
    "away_color": "#58a6ff",
    "predicted": {
      "away_win": 0.5406,
      "draw": 0.3005,
      "home_win": 0.1589
    },
    "actual": {
      "home_goals": 1,
      "away_goals": 1,
      "outcome": "D"
    },
    "is_upset": false,
    "has_statsbomb": false,
    "statsbomb_match_id": null
  },
  {
    "match_id": "FIN-20200508-MAR-INT",
    "date": "2020-05-08",
    "home": "Mariehamn",
    "away": "Inter Turku",
    "home_color": "#58a6ff",
    "away_color": "#010e80",
    "predicted": {
      "away_win": 0.6463,
      "draw": 0.2126,
      "home_win": 0.1411
    },
    "actual": {
      "home_goals": 2,
      "away_goals": 0,
      "outcome": "H"
    },
    "is_upset": true,
    "has_statsbomb": false,
    "statsbomb_match_id": null
  },
  {
    "match_id": "FIN-20200508-ILV-ROV",
    "date": "2020-05-08",
    "home": "Ilves",
    "away": "Rovaniemi",
    "home_color": "#58a6ff",
    "away_color": "#58a6ff",
    "predicted": {
      "away_win": 0.127,
      "draw": 0.3143,
      "home_win": 0.5588
    },
    "actual": {
      "home_goals": 1,
      "away_goals": 0,
      "outcome": "H"
    },
    "is_upset": false,
    "has_statsbomb": false,
    "statsbomb_match_id": null
  },
  {
    "match_id": "FIN-20200510-KUP-ILV",
    "date": "2020-05-10",
    "home": "KuPS",
    "away": "Ilves",
    "home_color": "#58a6ff",
    "away_color": "#58a6ff",
    "predicted": {
      "away_win": 0.2806,
      "draw": 0.3557,
      "home_win": 0.3637
    },
    "actual": {
      "home_goals": 1,
      "away_goals": 1,
      "outcome": "D"
    },
    "is_upset": false,
    "has_statsbomb": false,
    "statsbomb_match_id": null
  },
  {
    "match_id": "FIN-20200608-TPS-HON",
    "date": "2020-06-08",
    "home": "TPS",
    "away": "Honka",
    "home_color": "#58a6ff",
    "away_color": "#58a6ff",
    "predicted": {
      "away_win": 0.5184,
      "draw": 0.3172,
      "home_win": 0.1644
    },
    "actual": {
      "home_goals": 0,
      "away_goals": 2,
      "outcome": "A"
    },
    "is_upset": false,
    "has_statsbomb": false,
    "statsbomb_match_id": null
  },
  {
    "match_id": "FIN-20200608-HJK-LAH",
    "date": "2020-06-08",
    "home": "HJK",
    "away": "Lahti",
    "home_color": "#58a6ff",
    "away_color": "#58a6ff",
    "predicted": {
      "away_win": 0.1079,
      "draw": 0.2,
      "home_win": 0.692
    },
    "actual": {
      "home_goals": 1,
      "away_goals": 1,
      "outcome": "D"
    },
    "is_upset": true,
    "has_statsbomb": false,
    "statsbomb_match_id": null
  },
  {
    "match_id": "FIN-20200707-TPS-ILV",
    "date": "2020-07-07",
    "home": "TPS",
    "away": "Ilves",
    "home_color": "#58a6ff",
    "away_color": "#58a6ff",
    "predicted": {
      "away_win": 0.519,
      "draw": 0.3168,
      "home_win": 0.1642
    },
    "actual": {
      "home_goals": 0,
      "away_goals": 1,
      "outcome": "A"
    },
    "is_upset": false,
    "has_statsbomb": false,
    "statsbomb_match_id": null
  },
  {
    "match_id": "FIN-20200707-KUP-INT",
    "date": "2020-07-07",
    "home": "KuPS",
    "away": "Inter Turku",
    "home_color": "#58a6ff",
    "away_color": "#010e80",
    "predicted": {
      "away_win": 0.2877,
      "draw": 0.3303,
      "home_win": 0.382
    },
    "actual": {
      "home_goals": 1,
      "away_goals": 0,
      "outcome": "H"
    },
    "is_upset": false,
    "has_statsbomb": false,
    "statsbomb_match_id": null
  },
  {
    "match_id": "FIN-20200717-ILV-KUP",
    "date": "2020-07-17",
    "home": "Ilves",
    "away": "KuPS",
    "home_color": "#58a6ff",
    "away_color": "#58a6ff",
    "predicted": {
      "away_win": 0.4125,
      "draw": 0.3623,
      "home_win": 0.2252
    },
    "actual": {
      "home_goals": 0,
      "away_goals": 0,
      "outcome": "D"
    },
    "is_upset": false,
    "has_statsbomb": false,
    "statsbomb_match_id": null
  },
  {
    "match_id": "FIN-20200717-ROV-HAK",
    "date": "2020-07-17",
    "home": "Rovaniemi",
    "away": "Haka",
    "home_color": "#58a6ff",
    "away_color": "#58a6ff",
    "predicted": {
      "away_win": 0.5353,
      "draw": 0.2983,
      "home_win": 0.1664
    },
    "actual": {
      "home_goals": 2,
      "away_goals": 2,
      "outcome": "D"
    },
    "is_upset": true,
    "has_statsbomb": false,
    "statsbomb_match_id": null
  },
  {
    "match_id": "FIN-20200717-SJK-MAR",
    "date": "2020-07-17",
    "home": "SJK",
    "away": "Mariehamn",
    "home_color": "#58a6ff",
    "away_color": "#58a6ff",
    "predicted": {
      "away_win": 0.2839,
      "draw": 0.3514,
      "home_win": 0.3647
    },
    "actual": {
      "home_goals": 1,
      "away_goals": 2,
      "outcome": "A"
    },
    "is_upset": true,
    "has_statsbomb": false,
    "statsbomb_match_id": null
  },
  {
    "match_id": "FIN-20200717-INT-HJK",
    "date": "2020-07-17",
    "home": "Inter Turku",
    "away": "HJK",
    "home_color": "#010e80",
    "away_color": "#58a6ff",
    "predicted": {
      "away_win": 0.5438,
      "draw": 0.2873,
      "home_win": 0.1689
    },
    "actual": {
      "home_goals": 1,
      "away_goals": 0,
      "outcome": "H"
    },
    "is_upset": true,
    "has_statsbomb": false,
    "statsbomb_match_id": null
  },
  {
    "match_id": "FIN-20200718-HIF-LAH",
    "date": "2020-07-18",
    "home": "HIFK",
    "away": "Lahti",
    "home_color": "#58a6ff",
    "away_color": "#58a6ff",
    "predicted": {
      "away_win": 0.3266,
      "draw": 0.3745,
      "home_win": 0.2988
    },
    "actual": {
      "home_goals": 0,
      "away_goals": 3,
      "outcome": "A"
    },
    "is_upset": false,
    "has_statsbomb": false,
    "statsbomb_match_id": null
  },
  {
    "match_id": "FIN-20200718-HON-TPS",
    "date": "2020-07-18",
    "home": "Honka",
    "away": "TPS",
    "home_color": "#58a6ff",
    "away_color": "#58a6ff",
    "predicted": {
      "away_win": 0.1931,
      "draw": 0.2946,
      "home_win": 0.5124
    },
    "actual": {
      "home_goals": 3,
      "away_goals": 1,
      "outcome": "H"
    },
    "is_upset": false,
    "has_statsbomb": false,
    "statsbomb_match_id": null
  },
  {
    "match_id": "FIN-20200721-ROV-ILV",
    "date": "2020-07-21",
    "home": "Rovaniemi",
    "away": "Ilves",
    "home_color": "#58a6ff",
    "away_color": "#58a6ff",
    "predicted": {
      "away_win": 0.6298,
      "draw": 0.2444,
      "home_win": 0.1258
    },
    "actual": {
      "home_goals": 1,
      "away_goals": 1,
      "outcome": "D"
    },
    "is_upset": true,
    "has_statsbomb": false,
    "statsbomb_match_id": null
  },
  {
    "match_id": "FIN-20200722-TPS-HJK",
    "date": "2020-07-22",
    "home": "TPS",
    "away": "HJK",
    "home_color": "#58a6ff",
    "away_color": "#58a6ff",
    "predicted": {
      "away_win": 0.7034,
      "draw": 0.2058,
      "home_win": 0.0909
    },
    "actual": {
      "home_goals": 0,
      "away_goals": 2,
      "outcome": "A"
    },
    "is_upset": false,
    "has_statsbomb": false,
    "statsbomb_match_id": null
  },
  {
    "match_id": "FIN-20200722-HON-INT",
    "date": "2020-07-22",
    "home": "Honka",
    "away": "Inter Turku",
    "home_color": "#58a6ff",
    "away_color": "#010e80",
    "predicted": {
      "away_win": 0.2986,
      "draw": 0.3592,
      "home_win": 0.3422
    },
    "actual": {
      "home_goals": 1,
      "away_goals": 1,
      "outcome": "D"
    },
    "is_upset": false,
    "has_statsbomb": false,
    "statsbomb_match_id": null
  },
  {
    "match_id": "FIN-20200722-KUP-LAH",
    "date": "2020-07-22",
    "home": "KuPS",
    "away": "Lahti",
    "home_color": "#58a6ff",
    "away_color": "#58a6ff",
    "predicted": {
      "away_win": 0.1911,
      "draw": 0.2934,
      "home_win": 0.5155
    },
    "actual": {
      "home_goals": 3,
      "away_goals": 0,
      "outcome": "H"
    },
    "is_upset": false,
    "has_statsbomb": false,
    "statsbomb_match_id": null
  },
  {
    "match_id": "FIN-20200722-HIF-SJK",
    "date": "2020-07-22",
    "home": "HIFK",
    "away": "SJK",
    "home_color": "#58a6ff",
    "away_color": "#58a6ff",
    "predicted": {
      "away_win": 0.3286,
      "draw": 0.3858,
      "home_win": 0.2857
    },
    "actual": {
      "home_goals": 2,
      "away_goals": 1,
      "outcome": "H"
    },
    "is_upset": true,
    "has_statsbomb": false,
    "statsbomb_match_id": null
  },
  {
    "match_id": "FIN-20200722-MAR-HAK",
    "date": "2020-07-22",
    "home": "Mariehamn",
    "away": "Haka",
    "home_color": "#58a6ff",
    "away_color": "#58a6ff",
    "predicted": {
      "away_win": 0.3924,
      "draw": 0.3299,
      "home_win": 0.2778
    },
    "actual": {
      "home_goals": 2,
      "away_goals": 2,
      "outcome": "D"
    },
    "is_upset": false,
    "has_statsbomb": false,
    "statsbomb_match_id": null
  },
  {
    "match_id": "FIN-20200725-TPS-LAH",
    "date": "2020-07-25",
    "home": "TPS",
    "away": "Lahti",
    "home_color": "#58a6ff",
    "away_color": "#58a6ff",
    "predicted": {
      "away_win": 0.3663,
      "draw": 0.3792,
      "home_win": 0.2545
    },
    "actual": {
      "home_goals": 1,
      "away_goals": 3,
      "outcome": "A"
    },
    "is_upset": false,
    "has_statsbomb": false,
    "statsbomb_match_id": null
  },
  {
    "match_id": "FIN-20200725-HJK-ILV",
    "date": "2020-07-25",
    "home": "HJK",
    "away": "Ilves",
    "home_color": "#58a6ff",
    "away_color": "#58a6ff",
    "predicted": {
      "away_win": 0.1988,
      "draw": 0.2932,
      "home_win": 0.508
    },
    "actual": {
      "home_goals": 2,
      "away_goals": 0,
      "outcome": "H"
    },
    "is_upset": false,
    "has_statsbomb": false,
    "statsbomb_match_id": null
  },
  {
    "match_id": "FIN-20200726-HON-ROV",
    "date": "2020-07-26",
    "home": "Honka",
    "away": "Rovaniemi",
    "home_color": "#58a6ff",
    "away_color": "#58a6ff",
    "predicted": {
      "away_win": 0.1334,
      "draw": 0.3127,
      "home_win": 0.5539
    },
    "actual": {
      "home_goals": 1,
      "away_goals": 0,
      "outcome": "H"
    },
    "is_upset": false,
    "has_statsbomb": false,
    "statsbomb_match_id": null
  },
  {
    "match_id": "FIN-20200726-KUP-SJK",
    "date": "2020-07-26",
    "home": "KuPS",
    "away": "SJK",
    "home_color": "#58a6ff",
    "away_color": "#58a6ff",
    "predicted": {
      "away_win": 0.1698,
      "draw": 0.2878,
      "home_win": 0.5424
    },
    "actual": {
      "home_goals": 2,
      "away_goals": 1,
      "outcome": "H"
    },
    "is_upset": false,
    "has_statsbomb": false,
    "statsbomb_match_id": null
  },
  {
    "match_id": "FIN-20200726-MAR-HIF",
    "date": "2020-07-26",
    "home": "Mariehamn",
    "away": "HIFK",
    "home_color": "#58a6ff",
    "away_color": "#58a6ff",
    "predicted": {
      "away_win": 0.4156,
      "draw": 0.3316,
      "home_win": 0.2528
    },
    "actual": {
      "home_goals": 0,
      "away_goals": 3,
      "outcome": "A"
    },
    "is_upset": false,
    "has_statsbomb": false,
    "statsbomb_match_id": null
  },
  {
    "match_id": "FIN-20200726-HAK-INT",
    "date": "2020-07-26",
    "home": "Haka",
    "away": "Inter Turku",
    "home_color": "#58a6ff",
    "away_color": "#010e80",
    "predicted": {
      "away_win": 0.4898,
      "draw": 0.3052,
      "home_win": 0.2049
    },
    "actual": {
      "home_goals": 0,
      "away_goals": 2,
      "outcome": "A"
    },
    "is_upset": false,
    "has_statsbomb": false,
    "statsbomb_match_id": null
  }
]